{
	"name": "AzureMySqlTable1_Employee",
	"properties": {
		"linkedServiceName": {
			"referenceName": "Azure_DWH_HR_link",
			"type": "LinkedServiceReference"
		},
		"parameters": {
			"cwtablename": {
				"type": "String",
				"defaultValue": "dim_employee"
			}
		},
		"annotations": [],
		"type": "AzureMySqlTable",
		"schema": [
			{
				"name": "employee_key",
				"type": "bigint",
				"precision": 0,
				"scale": 0
			},
			{
				"name": "source_system_code",
				"type": "varchar",
				"precision": 0,
				"scale": 0
			},
			{
				"name": "source_employee_id",
				"type": "varchar",
				"precision": 0,
				"scale": 0
			},
			{
				"name": "company_id",
				"type": "varchar",
				"precision": 0,
				"scale": 0
			},
			{
				"name": "employee_code",
				"type": "varchar",
				"precision": 0,
				"scale": 0
			},
			{
				"name": "registration_number",
				"type": "varchar",
				"precision": 0,
				"scale": 0
			},
			{
				"name": "family_name",
				"type": "varchar",
				"precision": 0,
				"scale": 0
			},
			{
				"name": "last_name",
				"type": "varchar",
				"precision": 0,
				"scale": 0
			},
			{
				"name": "first_name",
				"type": "varchar",
				"precision": 0,
				"scale": 0
			},
			{
				"name": "gender",
				"type": "varchar",
				"precision": 0,
				"scale": 0
			},
			{
				"name": "birth_date",
				"type": "date",
				"precision": 0,
				"scale": 0
			},
			{
				"name": "nationality_id",
				"type": "int",
				"precision": 0,
				"scale": 0
			},
			{
				"name": "employment_status",
				"type": "varchar",
				"precision": 0,
				"scale": 0
			},
			{
				"name": "effective_start_date",
				"type": "datetime",
				"precision": 0,
				"scale": 0
			},
			{
				"name": "effective_end_date",
				"type": "datetime",
				"precision": 0,
				"scale": 0
			},
			{
				"name": "is_current_record",
				"type": "tinyint",
				"precision": 0,
				"scale": 0
			},
			{
				"name": "source_created_date",
				"type": "datetime",
				"precision": 0,
				"scale": 0
			},
			{
				"name": "source_updated_date",
				"type": "datetime",
				"precision": 0,
				"scale": 0
			},
			{
				"name": "dw_created_date",
				"type": "datetime",
				"precision": 0,
				"scale": 0
			},
			{
				"name": "dw_updated_date",
				"type": "datetime",
				"precision": 0,
				"scale": 0
			},
			{
				"name": "etl_batch_id",
				"type": "bigint",
				"precision": 0,
				"scale": 0
			}
		],
		"typeProperties": {
			"tableName": {
				"value": "@dataset().cwtablename",
				"type": "Expression"
			}
		}
	},
	"type": "Microsoft.DataFactory/factories/datasets"
}